uledgersdk/__init__.py
uledgersdk/core.py
uledgersdk/exceptions.py
uledgersdk/words/en.txt
uledgersdk/words/es.txt
uledgersdk/words/fr.txt
uledgersdk/words/it.txt
uledgersdk/words/pt.txt
uledgersdk-1.3.8.dist-info/METADATA
uledgersdk-1.3.8.dist-info/WHEEL
uledgersdk-1.3.8.dist-info/top_level.txt
uledgersdk-1.3.8.dist-info/RECORD
