Metadata-Version: 2.1
Name: uledgersdk
Version: 1.3.8
Summary: ULedger's Python SDK
Home-page: UNKNOWN
Author: Carlomagno Amaya
Author-email: carlomagno@uledger.io
License: MIT
Project-URL: Documentation, https://docs.uledger.io/python
Keywords: uledger sdk api
Platform: UNKNOWN
Classifier: Development Status :: 3 - Alpha
Classifier: Intended Audience :: Developers
Classifier: Programming Language :: Python :: 3.9
Requires-Python: >=3.9
Requires-Dist: requests
Requires-Dist: ecdsa
Requires-Dist: datetime
Requires-Dist: urllib3
Requires-Dist: cryptography
